{
  "openapi": "3.0.0",
  "info": {
    "title": "Solo API",
    "description": "API documentation for Solo note-taking application",
    "version": "1.2.0"
  },
  "servers": [
    {
      "url": "https://{hostname}",
      "variables": {
        "hostname": {
          "default": "localhost",
          "description": "Server hostname"
        }
      }
    }
  ],
  "components": {
    "securitySchemes": {
      "bearerAuth": {
        "type": "http",
        "scheme": "bearer",
        "bearerFormat": "JWT"
      }
    },
    "schemas": {
      "User": {
        "type": "object",
        "properties": {
          "id": {
            "type": "string",
            "format": "uuid"
          },
          "username": {
            "type": "string"
          },
          "password": {
            "type": "string",
            "format": "password"
          }
        },
        "required": ["username", "password"]
      },
      "LoginResponse": {
        "type": "object",
        "properties": {
          "token": {
            "type": "string"
          }
        }
      },
      "Note": {
        "type": "object",
        "properties": {
          "id": {
            "type": "string"
          },
          "title": {
            "type": "string"
          },
          "content": {
            "type": "string"
          },
          "createdAt": {
            "type": "string",
            "format": "date-time"
          },
          "tags": {
            "type": "array",
            "items": {
              "$ref": "#/components/schemas/Tag"
            }
          },
          "notebookId": {
            "type": "string"
          }
        }
      },
      "Notebook": {
        "type": "object",
        "properties": {
          "id": {
            "type": "string"
          },
          "name": {
            "type": "string"
          },
          "parentId": {
            "type": "string",
            "nullable": true
          },
          "isExpanded": {
            "type": "boolean"
          }
        }
      },
      "Tag": {
        "type": "object",
        "properties": {
          "id": {
            "type": "string"
          },
          "path": {
            "type": "string"
          }
        }
      },
      "SyncData": {
        "type": "object",
        "properties": {
          "notes": {
            "type": "array",
            "items": {
              "$ref": "#/components/schemas/Note"
            }
          },
          "notebooks": {
            "type": "array",
            "items": {
              "$ref": "#/components/schemas/Notebook"
            }
          }
        }
      },
      "Error": {
        "type": "object",
        "properties": {
          "error": {
            "type": "string"
          }
        }
      }
    }
  },
  "paths": {
    "/api/register": {
      "post": {
        "summary": "Register a new user",
        "requestBody": {
          "required": true,
          "content": {
            "application/json": {
              "schema": {
                "$ref": "#/components/schemas/User"
              }
            }
          }
        },
        "responses": {
          "201": {
            "description": "User registered successfully",
            "content": {
              "application/json": {
                "schema": {
                  "type": "object",
                  "properties": {
                    "message": {
                      "type": "string"
                    }
                  }
                }
              }
            }
          },
          "400": {
            "description": "Username already exists",
            "content": {
              "application/json": {
                "schema": {
                  "$ref": "#/components/schemas/Error"
                }
              }
            }
          }
        }
      }
    },
    "/api/login": {
      "post": {
        "summary": "Login and receive JWT token",
        "requestBody": {
          "required": true,
          "content": {
            "application/json": {
              "schema": {
                "$ref": "#/components/schemas/User"
              }
            }
          }
        },
        "responses": {
          "200": {
            "description": "Login successful",
            "content": {
              "application/json": {
                "schema": {
                  "$ref": "#/components/schemas/LoginResponse"
                }
              }
            }
          },
          "401": {
            "description": "Invalid credentials",
            "content": {
              "application/json": {
                "schema": {
                  "$ref": "#/components/schemas/Error"
                }
              }
            }
          }
        }
      }
    },
    "/api/data": {
      "get": {
        "summary": "Get user's synchronized data",
        "security": [
          {
            "bearerAuth": []
          }
        ],
        "responses": {
          "200": {
            "description": "User data retrieved successfully",
            "content": {
              "application/json": {
                "schema": {
                  "$ref": "#/components/schemas/SyncData"
                }
              }
            }
          },
          "401": {
            "description": "Unauthorized",
            "content": {
              "application/json": {
                "schema": {
                  "$ref": "#/components/schemas/Error"
                }
              }
            }
          }
        }
      },
      "post": {
        "summary": "Synchronize user data",
        "security": [
          {
            "bearerAuth": []
          }
        ],
        "requestBody": {
          "required": true,
          "content": {
            "application/json": {
              "schema": {
                "$ref": "#/components/schemas/SyncData"
              }
            }
          }
        },
        "responses": {
          "200": {
            "description": "Data synchronized successfully",
            "content": {
              "application/json": {
                "schema": {
                  "type": "object",
                  "properties": {
                    "message": {
                      "type": "string"
                    }
                  }
                }
              }
            }
          },
          "401": {
            "description": "Unauthorized",
            "content": {
              "application/json": {
                "schema": {
                  "$ref": "#/components/schemas/Error"
                }
              }
            }
          }
        }
      }
    },
    "/api/upload": {
      "post": {
        "summary": "Upload an image",
        "security": [
          {
            "bearerAuth": []
          }
        ],
        "requestBody": {
          "required": true,
          "content": {
            "multipart/form-data": {
              "schema": {
                "type": "object",
                "properties": {
                  "image": {
                    "type": "string",
                    "format": "binary"
                  }
                }
              }
            }
          }
        },
        "responses": {
          "200": {
            "description": "Image uploaded successfully",
            "content": {
              "application/json": {
                "schema": {
                  "type": "object",
                  "properties": {
                    "url": {
                      "type": "string"
                    }
                  }
                }
              }
            }
          },
          "401": {
            "description": "Unauthorized",
            "content": {
              "application/json": {
                "schema": {
                  "$ref": "#/components/schemas/Error"
                }
              }
            }
          }
        }
      }
    },
    "/api/images/{userId}/{imageId}": {
      "get": {
        "summary": "Get an uploaded image",
        "parameters": [
          {
            "name": "userId",
            "in": "path",
            "required": true,
            "schema": {
              "type": "string"
            }
          },
          {
            "name": "imageId",
            "in": "path",
            "required": true,
            "schema": {
              "type": "string"
            }
          }
        ],
        "responses": {
          "200": {
            "description": "Image retrieved successfully",
            "content": {
              "image/*": {
                "schema": {
                  "type": "string",
                  "format": "binary"
                }
              }
            }
          },
          "404": {
            "description": "Image not found",
            "content": {
              "application/json": {
                "schema": {
                  "$ref": "#/components/schemas/Error"
                }
              }
            }
          }
        }
      }
    }
  }
}